tkterm/__init__.py
tkterm/__main__.py
tkterm/icon.png
tkterm/tkterm.py
tkterm/version.py
tkterm/backend/InterpreterInterface.py
tkterm/backend/InterpreterShell.py
tkterm/backend/KThread.py
tkterm/backend/__init__.py
tkterm/img/app_icon.png
tkterm/img/case.png
tkterm/img/close.png
tkterm/img/close_tab.png
tkterm/img/hamburger.png
tkterm/img/linux.png
tkterm/img/new_tab.png
tkterm/img/next.png
tkterm/img/next_tab.png
tkterm/img/plus.png
tkterm/img/prev.png
tkterm/img/prev_tab.png
tkterm/img/regex.png
tkterm/img/screenshot.jpg
tkterm/img/search.png
tkterm/img/settings.png
tkterm/img/snapshot1.png
tkterm/img/snapshot2.png
tkterm/img/warn.png
tkterm/img/windows.png
tkterm/src/Config.py
tkterm/src/ExitDiaglogBox.py
tkterm/src/Interpreter.py
tkterm/src/Redirect.py
tkterm/src/RightClickContextMenu.py
tkterm/src/SearchBar.py
tkterm/src/TerminalScreen.py
tkterm/src/TerminalTab.py
tkterm/src/Tooltip.py
tkterm/src/Utils.py
tkterm/src/__init__.py
tkterm-0.0.0b2.dist-info/LICENSE
tkterm-0.0.0b2.dist-info/METADATA
tkterm-0.0.0b2.dist-info/WHEEL
tkterm-0.0.0b2.dist-info/top_level.txt
tkterm-0.0.0b2.dist-info/RECORD
