Metadata-Version: 2.1
Name: tkterm
Version: 0.0.0b2
Summary: Terminal emulator built on Tkinter library.
Home-page: https://github.com/dhanoosu/tkterm
Author: Dhanoo Surasarang
Author-email: dhanoo.surasarang@gmail.com
License: MIT
Project-URL: Documentation, https://github.com/dhanoosu/TkTerm/blob/master/README.md
Project-URL: Bug Tracker, https://github.com/dhanoosu/TkTerm/issues
Keywords: linux,shell,bash,cli,gui,terminal,command-line,tkinter,subprocess,tkinter-graphic-interface,terminal-emulator,ttk,commandprompt,tkinter-gui,tkinter-python,tkinter-terminal,tk-terminal,tkinter-shell,tkterminal
Classifier: Development Status :: 4 - Beta
Classifier: Intended Audience :: Developers
Classifier: Intended Audience :: Education
Classifier: Intended Audience :: End Users/Desktop
Classifier: License :: OSI Approved :: MIT License
Classifier: Topic :: Software Development :: Libraries :: Python Modules
Classifier: Programming Language :: Python :: 3
License-File: LICENSE
